[
    {
        "name": "HTV1",
        "logo": "https://vnrartv.github.io/icon/htv1.webp",
        "url": "https://vc.101vn.com/htv/htvcmb.php?id=2631"
    },
    {
        "name": "HTV2 Vie Vchannel",
        "logo": "https://vnrartv.github.io/icon/htv2.webp",
        "url": "http://203.162.123.188:8080/htv2/index.m3u8"
    },
    {
        "name": "HTV3",
        "logo": "https://vnrartv.github.io/icon/htv3.webp",
        "url": "https://vc.101vn.com/htv/htvcmb.php?id=2535"
    },
    {
        "name": "HTVKey",
        "logo": "https://vnrartv.github.io/icon/htvkey.webp",
        "url": "https://vc.101vn.com/htv/htvcmb.php?id=2528"
    },
    {
        "name": "HTV7",
        "logo": "https://vnrartv.github.io/icon/htv7.webp",
        "url": "https://vc.101vn.com/htv/htvcmb.php?id=256"
    },
    {
        "name": "HTV9",
        "logo": "https://vnrartv.github.io/icon/htv9.webp",
        "url": "http://203.162.123.188:8080/htv9/index.m3u8"
    },
    {
        "name": "HTV Thể Thao",
        "logo": "https://vnrartv.github.io/icon/htvtt.webp",
        "url": "https://tth.vn/HTVC-THE-THAO"
    }
]